CHANGES.rst
LICENSE
MANIFEST.in
README.rst
setup.cfg
setup.py
src/experimental/__init__.py
src/experimental.securityindexing.egg-info/PKG-INFO
src/experimental.securityindexing.egg-info/SOURCES.txt
src/experimental.securityindexing.egg-info/dependency_links.txt
src/experimental.securityindexing.egg-info/entry_points.txt
src/experimental.securityindexing.egg-info/namespace_packages.txt
src/experimental.securityindexing.egg-info/not-zip-safe
src/experimental.securityindexing.egg-info/requires.txt
src/experimental.securityindexing.egg-info/top_level.txt
src/experimental/securityindexing/__init__.py
src/experimental/securityindexing/adapters.py
src/experimental/securityindexing/configure.zcml
src/experimental/securityindexing/interfaces.py
src/experimental/securityindexing/patches.py
src/experimental/securityindexing/patches.zcml
src/experimental/securityindexing/shadowtree.py
src/experimental/securityindexing/subscribers.py
src/experimental/securityindexing/testing.py
src/experimental/securityindexing/utilities.py
src/experimental/securityindexing/Extensions/Install.py
src/experimental/securityindexing/Extensions/__init__.py
src/experimental/securityindexing/browser/__init__.py
src/experimental/securityindexing/browser/configure.zcml
src/experimental/securityindexing/browser/controlpanel.py
src/experimental/securityindexing/browser/resources/style.css
src/experimental/securityindexing/browser/templates/controlpanel_layout.pt
src/experimental/securityindexing/profiles/default/componentregistry.xml
src/experimental/securityindexing/profiles/default/controlpanel.xml
src/experimental/securityindexing/profiles/default/metadata.xml
src/experimental/securityindexing/profiles/default/toolset.xml
src/experimental/securityindexing/profiles/uninstall/componentregistry.xml
src/experimental/securityindexing/profiles/uninstall/metadata.xml
src/experimental/securityindexing/tests/__init__.py
src/experimental/securityindexing/tests/dx.py
src/experimental/securityindexing/tests/test_adapters.py
src/experimental/securityindexing/tests/test_controlpanel.py
src/experimental/securityindexing/tests/test_shadowtree.py
src/experimental/securityindexing/tests/test_subscribers.py
src/experimental/securityindexing/tests/test_uninstall.py
src/experimental/securityindexing/tests/test_utilities.py
src/experimental/securityindexing/tests/utils.py