Metadata-Version: 1.1
Name: experimental.securityindexing
Version: 0.6
Summary:       Optimises indexing of object security for a Plone site.
Home-page: https://github.com/ploneintranet/experimental.securityindexing
Author: Netsight Internet Solutions
Author-email: dev@netsight.co.uk
License: GPLv2
Platform: UNKNOWN
Classifier: Programming Language :: Python :: 2.7
Classifier: Framework :: Plone :: 4.0
Classifier: Framework :: Plone :: 4.1
Classifier: Framework :: Plone :: 4.2
Classifier: Framework :: Plone :: 4.3
